[{"App": "Bonza Poly Art - Tenkyu Animal Jam for Kids", "Category": "FAMILY", "Rating": 4.1, "Reviews": 22, "Size": "31M", "Installs": "1,000+", "Type": "Free", "Price": 0, "Content Rating": "Everyone", "Genres": "Puzzle", "Last Updated": "August 3, 2018", "Current Ver": "1.0.9", "Android Ver": "4.1 and up"}, {"App": "A.J. Styles HD Wallpapers 2018", "Category": "PHOTOGRAPHY", "Rating": "NaN", "Reviews": 1, "Size": "7.6M", "Installs": "100+", "Type": "Free", "Price": 0, "Content Rating": "Everyone", "Genres": "Photography", "Last Updated": "July 26, 2018", "Current Ver": 1, "Android Ver": "4.1 and up"}, {"App": "AJ Player", "Category": "VIDEO_PLAYERS", "Rating": 4.8, "Reviews": 18, "Size": "1.7M", "Installs": "100+", "Type": "Free", "Price": 0, "Content Rating": "Everyone", "Genres": "Video Players & Editors", "Last Updated": "April 22, 2018", "Current Ver": "1.6.3.1", "Android Ver": "5.0 and up"}, {"App": "AJ RETAILS", "Category": "SHOPPING", "Rating": 5, "Reviews": 9, "Size": "169k", "Installs": "10+", "Type": "Free", "Price": 0, "Content Rating": "Everyone", "Genres": "Shopping", "Last Updated": "June 1, 2018", "Current Ver": 18060104, "Android Ver": "2.2 and up"}, {"App": "Hey AJ! It's Bedtime!", "Category": "FAMILY", "Rating": 5, "Reviews": 1, "Size": "63M", "Installs": "10+", "Type": "Paid", "Price": "$4.99", "Content Rating": "Everyone", "Genres": "Education", "Last Updated": "April 4, 2018", "Current Ver": "1.0.59", "Android Ver": "2.3 and up"}, {"App": "AJ AUTO", "Category": "AUTO_AND_VEHICLES", "Rating": "NaN", "Reviews": 0, "Size": "7.7M", "Installs": "10+", "Type": "Free", "Price": 0, "Content Rating": "Everyone", "Genres": "Auto & Vehicles", "Last Updated": "February 27, 2017", "Current Ver": "1.0.0", "Android Ver": "4.0.3 and up"}, {"App": "AJ Percent Off Calculator", "Category": "SHOPPING", "Rating": 4.4, "Reviews": 134, "Size": "45k", "Installs": "10,000+", "Type": "Free", "Price": 0, "Content Rating": "Everyone", "Genres": "Shopping", "Last Updated": "June 4, 2013", "Current Ver": 1.2, "Android Ver": "2.2 and up"}, {"App": "AJ Nails Supply", "Category": "SHOPPING", "Rating": "NaN", "Reviews": 1, "Size": "6.6M", "Installs": "100+", "Type": "Free", "Price": 0, "Content Rating": "Everyone", "Genres": "Shopping", "Last Updated": "August 15, 2016", "Current Ver": 1, "Android Ver": "2.3.3 and up"}, {"App": "Aj.Petra", "Category": "COMMUNICATION", "Rating": "NaN", "Reviews": 5, "Size": "14M", "Installs": "100+", "Type": "Free", "Price": 0, "Content Rating": "Everyone", "Genres": "Communication", "Last Updated": "September 29, 2017", "Current Ver": "1.0.1", "Android Ver": "4.1 and up"}, {"App": "AJ Men's Grooming", "Category": "LIFESTYLE", "Rating": 5, "Reviews": 2, "Size": "22M", "Installs": "100+", "Type": "Free", "Price": 0, "Content Rating": "Everyone", "Genres": "Lifestyle", "Last Updated": "August 28, 2017", "Current Ver": 5, "Android Ver": "4.1 and up"}, {"App": "Watch Face Swiss AJ-6", "Category": "PERSONALIZATION", "Rating": 4.1, "Reviews": 21, "Size": "3.6M", "Installs": "100+", "Type": "Paid", "Price": "$0.99", "Content Rating": "Everyone", "Genres": "Personalization", "Last Updated": "September 20, 2017", "Current Ver": 1.35, "Android Ver": "4.3 and up"}, {"App": "AJ Rafael Music Lyrics", "Category": "FAMILY", "Rating": "NaN", "Reviews": 0, "Size": "8.4M", "Installs": "50+", "Type": "Free", "Price": 0, "Content Rating": "Everyone 10+", "Genres": "Entertainment", "Last Updated": "January 3, 2018", "Current Ver": 2, "Android Ver": "4.0.3 and up"}, {"App": "AJ Styles HD Wallpapers", "Category": "ART_AND_DESIGN", "Rating": 4.8, "Reviews": 48, "Size": "25M", "Installs": "5,000+", "Type": "Free", "Price": 0, "Content Rating": "Everyone", "Genres": "Art & Design", "Last Updated": "August 4, 2018", "Current Ver": "1.1.1", "Android Ver": "4.1 and up"}, {"App": "AJ and Alyssa", "Category": "LIFESTYLE", "Rating": "NaN", "Reviews": 0, "Size": "475k", "Installs": "100+", "Type": "Free", "Price": 0, "Content Rating": "Everyone", "Genres": "Lifestyle", "Last Updated": "June 1, 2017", "Current Ver": "1.0.0", "Android Ver": "2.3.3 and up"}, {"App": "A.J. Green Wallpapers 4 Fans", "Category": "LIFESTYLE", "Rating": "NaN", "Reviews": 0, "Size": "4.3M", "Installs": "5+", "Type": "Free", "Price": 0, "Content Rating": "Everyone", "Genres": "Lifestyle", "Last Updated": "May 26, 2018", "Current Ver": 1, "Android Ver": "4.0 and up"}, {"App": "AJ Gray Icon Pack", "Category": "PERSONALIZATION", "Rating": 4.8, "Reviews": 5, "Size": "35M", "Installs": "50+", "Type": "Paid", "Price": "$0.99", "Content Rating": "Everyone", "Genres": "Personalization", "Last Updated": "April 22, 2018", "Current Ver": 1.1, "Android Ver": "4.1 and up"}, {"App": "AJ Styles Wallpaper 2018 - AJ Styles HD Wallpaper", "Category": "ART_AND_DESIGN", "Rating": 4, "Reviews": 18, "Size": "3.6M", "Installs": "1,000+", "Type": "Free", "Price": 0, "Content Rating": "Everyone", "Genres": "Art & Design", "Last Updated": "March 22, 2018", "Current Ver": 1.1, "Android Ver": "4.0 and up"}, {"App": "A-J Media Vault", "Category": "BOOKS_AND_REFERENCE", "Rating": "NaN", "Reviews": 1, "Size": "24M", "Installs": "50+", "Type": "Free", "Price": 0, "Content Rating": "Everyone", "Genres": "Books & Reference", "Last Updated": "January 4, 2017", "Current Ver": "5.62.1", "Android Ver": "4.0.3 and up"}, {"App": "AJ Gray Dark Icon Pack", "Category": "PERSONALIZATION", "Rating": 5, "Reviews": 2, "Size": "35M", "Installs": "10+", "Type": "Paid", "Price": "$0.99", "Content Rating": "Everyone", "Genres": "Personalization", "Last Updated": "April 29, 2018", "Current Ver": 1.1, "Android Ver": "4.1 and up"}, {"App": "Little Pets Animal Guardians", "Category": "FAMILY", "Rating": 4.6, "Reviews": 18893, "Size": "91M", "Installs": "100,000+", "Type": "Free", "Price": 0, "Content Rating": "Everyone", "Genres": "Casual;Pretend Play", "Last Updated": "June 9, 2018", "Current Ver": "1.4.1", "Android Ver": "4.0.3 and up"}, {"App": "AJ-COMICS", "Category": "FOOD_AND_DRINK", "Rating": "NaN", "Reviews": 0, "Size": "27M", "Installs": "5+", "Type": "Free", "Price": 0, "Content Rating": "Everyone", "Genres": "Food & Drink", "Last Updated": "July 13, 2018", "Current Ver": "0.1.0", "Android Ver": "4.4 and up"}, {"App": "AJ Blue Icon Pack", "Category": "PERSONALIZATION", "Rating": 5, "Reviews": 4, "Size": "31M", "Installs": "50+", "Type": "Paid", "Price": "$0.99", "Content Rating": "Everyone", "Genres": "Personalization", "Last Updated": "April 27, 2018", "Current Ver": 1.1, "Android Ver": "4.1 and up"}, {"App": "AJ Tracey Music and Lyrics", "Category": "FAMILY", "Rating": "NaN", "Reviews": 0, "Size": "2.7M", "Installs": "5+", "Type": "Free", "Price": 0, "Content Rating": "Teen", "Genres": "Entertainment", "Last Updated": "June 7, 2018", "Current Ver": 1, "Android Ver": "4.0.3 and up"}, {"App": "AJ Turquoise Dark Icon Pack", "Category": "PERSONALIZATION", "Rating": "NaN", "Reviews": 0, "Size": "32M", "Installs": "10+", "Type": "Paid", "Price": "$0.99", "Content Rating": "Everyone", "Genres": "Personalization", "Last Updated": "May 1, 2018", "Current Ver": 1.1, "Android Ver": "4.1 and up"}, {"App": "AJ\u00eb\u00a0\u0152\u064a\u201e\u00b0\u0649\u00b9\u00b4 \u00eb\u00b2\u2022\u0649\u200c\u00b8 \u0649\u00b9\u00b4\u0649\u2026\u00b0\u0649\u2013\u00b4\u00eb\u00a7\u067e", "Category": "MAPS_AND_NAVIGATION", "Rating": "NaN", "Reviews": 0, "Size": "27M", "Installs": "10+", "Type": "Free", "Price": 0, "Content Rating": "Everyone", "Genres": "Maps & Navigation", "Last Updated": "July 30, 2018", "Current Ver": "1.0.0.0", "Android Ver": "4.3 and up"}, {"App": "My Wild Pet: Online Animal Sim", "Category": "FAMILY", "Rating": 4.5, "Reviews": 26916, "Size": "67M", "Installs": "500,000+", "Type": "Free", "Price": 0, "Content Rating": "Everyone", "Genres": "Casual;Pretend Play", "Last Updated": "March 17, 2017", "Current Ver": 2.7, "Android Ver": "4.0.3 and up"}, {"App": "AJ Rafael Music Lessons", "Category": "FAMILY", "Rating": 5, "Reviews": 1, "Size": "8.2M", "Installs": "10+", "Type": "Free", "Price": 0, "Content Rating": "Everyone", "Genres": "Entertainment", "Last Updated": "November 29, 2017", "Current Ver": "1.2.1", "Android Ver": "4.1 and up"}]