[{"App": "Mizanul-Hikm\u0629\u2122t 2-ci cild", "Category": "LIBRARIES_AND_DEMO", "Rating": "NaN", "Reviews": 16, "Size": "743k", "Installs": "1,000+", "Type": "Free", "Price": 0, "Content Rating": "Everyone", "Genres": "Libraries & Demo", "Last Updated": "January 4, 2017", "Current Ver": 1, "Android Ver": "1.6 and up"}, {"App": "CI On The Go", "Category": "NEWS_AND_MAGAZINES", "Rating": 3, "Reviews": 2, "Size": "14M", "Installs": "100+", "Type": "Free", "Price": 0, "Content Rating": "Everyone", "Genres": "News & Magazines", "Last Updated": "July 18, 2018", "Current Ver": "v4.30.0.8", "Android Ver": "5.0 and up"}, {"App": "CJ SO COOL", "Category": "FAMILY", "Rating": 4.5, "Reviews": 145, "Size": "14M", "Installs": "10,000+", "Type": "Free", "Price": 0, "Content Rating": "Everyone", "Genres": "Entertainment", "Last Updated": "July 11, 2018", "Current Ver": 1, "Android Ver": "4.2 and up"}, {"App": "CJ Fitness", "Category": "HEALTH_AND_FITNESS", "Rating": 2.4, "Reviews": 221, "Size": "43M", "Installs": "10,000+", "Type": "Free", "Price": 0, "Content Rating": "Everyone", "Genres": "Health & Fitness", "Last Updated": "February 14, 2018", "Current Ver": "4.3.0", "Android Ver": "4.1 and up"}, {"App": "CJ: Strike Back", "Category": "GAME", "Rating": 4.3, "Reviews": 29330, "Size": "6.9M", "Installs": "1,000,000+", "Type": "Free", "Price": 0, "Content Rating": "Everyone", "Genres": "Action", "Last Updated": "August 17, 2012", "Current Ver": "1.0.9", "Android Ver": "2.0.1 and up"}, {"App": "The Grand Wars: San Andreas", "Category": "GAME", "Rating": 3.9, "Reviews": 29990, "Size": "96M", "Installs": "1,000,000+", "Type": "Free", "Price": 0, "Content Rating": "Teen", "Genres": "Action", "Last Updated": "December 8, 2017", "Current Ver": "Varies with device", "Android Ver": "2.3 and up"}, {"App": "CJ Fallon eBook Reader", "Category": "FAMILY", "Rating": 1.9, "Reviews": 76, "Size": "14M", "Installs": "5,000+", "Type": "Free", "Price": 0, "Content Rating": "Everyone", "Genres": "Education", "Last Updated": "February 13, 2014", "Current Ver": "2.2.1", "Android Ver": "3.0 and up"}, {"App": "Grand Theft Auto: San Andreas", "Category": "GAME", "Rating": 4.4, "Reviews": 348962, "Size": "26M", "Installs": "1,000,000+", "Type": "Paid", "Price": "$6.99", "Content Rating": "Mature 17+", "Genres": "Action", "Last Updated": "March 21, 2015", "Current Ver": 1.08, "Android Ver": "3.0 and up"}, {"App": "CJ Gospel Hour", "Category": "SOCIAL", "Rating": 5, "Reviews": 7, "Size": "18M", "Installs": "100+", "Type": "Free", "Price": 0, "Content Rating": "Everyone", "Genres": "Social", "Last Updated": "July 25, 2018", "Current Ver": 1, "Android Ver": "4.4 and up"}, {"App": "CJ's Tire & Automotive", "Category": "AUTO_AND_VEHICLES", "Rating": 4, "Reviews": 5, "Size": "34M", "Installs": "1,000+", "Type": "Free", "Price": 0, "Content Rating": "Everyone", "Genres": "Auto & Vehicles", "Last Updated": "July 30, 2018", "Current Ver": 2.8, "Android Ver": "2.3.3 and up"}, {"App": "CJ Camcorder", "Category": "VIDEO_PLAYERS", "Rating": 4.7, "Reviews": 3, "Size": "2.8M", "Installs": "500+", "Type": "Free", "Price": 0, "Content Rating": "Everyone", "Genres": "Video Players & Editors", "Last Updated": "November 26, 2017", "Current Ver": 1, "Android Ver": "4.0 and up"}, {"App": "The Grand Way", "Category": "GAME", "Rating": 3.9, "Reviews": 1995, "Size": "92M", "Installs": "500,000+", "Type": "Free", "Price": 0, "Content Rating": "Teen", "Genres": "Action", "Last Updated": "July 3, 2018", "Current Ver": 1.9, "Android Ver": "4.1 and up"}, {"App": "CJ'S TIRE AND AUTO INC.", "Category": "PRODUCTIVITY", "Rating": 5, "Reviews": 5, "Size": "11M", "Installs": "100+", "Type": "Free", "Price": 0, "Content Rating": "Everyone", "Genres": "Productivity", "Last Updated": "May 30, 2018", "Current Ver": "1.0.1", "Android Ver": "4.1 and up"}, {"App": "CJ Browser - Fast & Private", "Category": "COMMUNICATION", "Rating": 4.2, "Reviews": 5, "Size": "15M", "Installs": "100+", "Type": "Free", "Price": 0, "Content Rating": "Everyone", "Genres": "Communication", "Last Updated": "November 7, 2017", "Current Ver": 1, "Android Ver": "4.0 and up"}, {"App": "CJ WOW SHOP", "Category": "SHOPPING", "Rating": 4.2, "Reviews": 2099, "Size": "4.0M", "Installs": "100,000+", "Type": "Free", "Price": 0, "Content Rating": "Everyone", "Genres": "Shopping", "Last Updated": "December 23, 2017", "Current Ver": "1.1.1", "Android Ver": "4.0.3 and up"}, {"App": "Gold Teeth Photo Editor", "Category": "PHOTOGRAPHY", "Rating": 2.8, "Reviews": 1022, "Size": "3.8M", "Installs": "100,000+", "Type": "Free", "Price": 0, "Content Rating": "Everyone", "Genres": "Photography", "Last Updated": "August 24, 2016", "Current Ver": 2, "Android Ver": "2.3 and up"}, {"App": "CJ VLC HD Remote (+ Stream)", "Category": "VIDEO_PLAYERS", "Rating": 4.2, "Reviews": 4074, "Size": "1.3M", "Installs": "500,000+", "Type": "Free", "Price": 0, "Content Rating": "Everyone", "Genres": "Video Players & Editors", "Last Updated": "November 13, 2013", "Current Ver": "1.2.4", "Android Ver": "2.1 and up"}, {"App": "CJ DVD Rentals", "Category": "COMMUNICATION", "Rating": 1, "Reviews": 5, "Size": "13M", "Installs": "100+", "Type": "Free", "Price": 0, "Content Rating": "Everyone", "Genres": "Communication", "Last Updated": "October 6, 2017", "Current Ver": 1, "Android Ver": "4.1 and up"}, {"App": "San Andreas City : Auto Theft Car gangster", "Category": "GAME", "Rating": 3.9, "Reviews": 923, "Size": "67M", "Installs": "100,000+", "Type": "Free", "Price": 0, "Content Rating": "Teen", "Genres": "Action", "Last Updated": "July 17, 2018", "Current Ver": 1.4, "Android Ver": "4.1 and up"}, {"App": "Miami Crime Vice Town", "Category": "GAME", "Rating": 4.1, "Reviews": 154519, "Size": "99M", "Installs": "10,000,000+", "Type": "Free", "Price": 0, "Content Rating": "Mature 17+", "Genres": "Action", "Last Updated": "May 9, 2017", "Current Ver": 1.4, "Android Ver": "2.3 and up"}, {"App": "CJ Poker Odds Calculator", "Category": "GAME", "Rating": 4.1, "Reviews": 207, "Size": "116k", "Installs": "50,000+", "Type": "Free", "Price": 0, "Content Rating": "Everyone", "Genres": "Card", "Last Updated": "January 30, 2011", "Current Ver": 1.2, "Android Ver": "1.6 and up"}, {"App": "Commission Manager", "Category": "PRODUCTIVITY", "Rating": 3.2, "Reviews": 12, "Size": "2.2M", "Installs": "1,000+", "Type": "Free", "Price": 0, "Content Rating": "Everyone", "Genres": "Productivity", "Last Updated": "March 26, 2015", "Current Ver": "1.0.0.0", "Android Ver": "2.3.3 and up"}, {"App": "CJ Apps", "Category": "BUSINESS", "Rating": "NaN", "Reviews": 0, "Size": "24M", "Installs": "10+", "Type": "Free", "Price": 0, "Content Rating": "Everyone", "Genres": "Business", "Last Updated": "April 10, 2018", "Current Ver": 2.1, "Android Ver": "4.1 and up"}, {"App": "The CJ Rubric", "Category": "HEALTH_AND_FITNESS", "Rating": 5, "Reviews": 5, "Size": "43M", "Installs": "100+", "Type": "Free", "Price": 0, "Content Rating": "Everyone", "Genres": "Health & Fitness", "Last Updated": "December 5, 2017", "Current Ver": "The CJ Rubric 7.12.0", "Android Ver": "4.1 and up"}, {"App": "Pekalongan CJ", "Category": "SOCIAL", "Rating": "NaN", "Reviews": 0, "Size": "5.9M", "Installs": "0+", "Type": "Free", "Price": 0, "Content Rating": "Teen", "Genres": "Social", "Last Updated": "July 21, 2018", "Current Ver": "0.0.1", "Android Ver": "4.4 and up"}, {"App": "CJ's Coffee Cafe", "Category": "TRAVEL_AND_LOCAL", "Rating": 5, "Reviews": 6, "Size": "2.4M", "Installs": "500+", "Type": "Free", "Price": 0, "Content Rating": "Everyone", "Genres": "Travel & Local", "Last Updated": "August 21, 2017", "Current Ver": "7.5.0", "Android Ver": "4.0.3 and up"}, {"App": "Gangster City Auto Theft", "Category": "GAME", "Rating": 4.3, "Reviews": 350, "Size": "67M", "Installs": "50,000+", "Type": "Free", "Price": 0, "Content Rating": "Everyone", "Genres": "Action", "Last Updated": "July 27, 2018", "Current Ver": "Varies with device", "Android Ver": "4.0.3 and up"}]